{
    "_links": {
        "self": {
            "href": "http:\/\/default\/admin\/structure\/menu\/item\/9\/edit?_format=hal_json"
        },
        "type": {
            "href": "http:\/\/drupal.org\/rest\/type\/menu_link_content\/main"
        }
    },
    "id": [
        {
            "value": 9
        }
    ],
    "uuid": [
        {
            "value": "823b1d5f-9c71-4c9a-8c45-8e6193c54742"
        }
    ],
    "langcode": [
        {
            "value": "en",
            "lang": "en"
        }
    ],
    "bundle": [
        {
            "target_id": "main"
        }
    ],
    "enabled": [
        {
            "value": true
        }
    ],
    "title": [
        {
            "value": "Tools",
            "lang": "en"
        }
    ],
    "description": [
        {
            "value": "Tools",
            "lang": "en"
        }
    ],
    "menu_name": [
        {
            "value": "main"
        }
    ],
    "link": [
        {
            "uri": "internal:#tools",
            "title": "",
            "options": []
        }
    ],
    "external": [
        {
            "value": false
        }
    ],
    "rediscover": [
        {
            "value": true
        }
    ],
    "weight": [
        {
            "value": 5
        }
    ],
    "expanded": [
        {
            "value": false
        }
    ],
    "changed": [
        {
            "value": "2019-01-17T12:47:12+00:00",
            "lang": "en",
            "format": "Y-m-d\\TH:i:sP"
        }
    ],
    "default_langcode": [
        {
            "value": true,
            "lang": "en"
        }
    ],
    "view_mode": [
        {
            "value": "default",
            "lang": "en"
        }
    ]
}